systrack/__init__.py
systrack/dashboard.py
systrack/hardware_info.py
systrack/main.py
systrack/system_monitor.py
systrack/utils.py
systracker-0.2.7.dist-info/LICENSE
systracker-0.2.7.dist-info/METADATA
systracker-0.2.7.dist-info/WHEEL
systracker-0.2.7.dist-info/entry_points.txt
systracker-0.2.7.dist-info/top_level.txt
systracker-0.2.7.dist-info/RECORD
